aioyoufone/__init__.py
aioyoufone/client.py
aioyoufone/const.py
aioyoufone-0.4.3.dist-info/LICENSE
aioyoufone-0.4.3.dist-info/METADATA
aioyoufone-0.4.3.dist-info/WHEEL
aioyoufone-0.4.3.dist-info/top_level.txt
aioyoufone-0.4.3.dist-info/RECORD
