Metadata-Version: 2.1
Name: aioyoufone
Version: 0.4.3
Summary: Module to communicate to the Youfone API
Home-page: https://github.com/geertmeersman/aioyoufone
Author: Geert Meersman
Author-email: geertmeersman@gmail.com
License: MIT
Classifier: Programming Language :: Python :: 3
Classifier: License :: OSI Approved :: Apache Software License
Classifier: Operating System :: OS Independent
License-File: LICENSE
Requires-Dist: aiohttp
Requires-Dist: pip<24.3,>=8.0.3
Requires-Dist: ruff==0.6.9
